{"name": "HoldEscOnline", "description": "During VS Network matches, pressing Esc will instantly leave the match.\nTo avoid accidental Esc presses, this mod will change the Esc press into a 2 seconds hold.", "author": "PC_volt", "repositories": [{"type": "github", "owner": "soku-launcher-modpacks", "repo": "HoldEscOnline"}], "versionNumbers": ["1.2.0"], "recommendedVersionNumber": "1.2.0", "descriptionI18n": [{"language": "en", "content": "During VS Network matches, pressing Esc will instantly leave the match.\nTo avoid accidental Esc presses, this mod will change the Esc press into a 2 seconds hold."}]}